dash_wrapper/__init__.py
dash_wrapper/_wrapper.py
dash_wrapper/dash_bio/__init__.py
dash_wrapper/dash_bio/_wrapper.py
dash_wrapper/dash_bootstrap_components/__init__.py
dash_wrapper/dash_bootstrap_components/_wrapper.py
dash_wrapper/dash_canvas/__init__.py
dash_wrapper/dash_canvas/_wrapper.py
dash_wrapper/dash_core_components/__init__.py
dash_wrapper/dash_core_components/_wrapper.py
dash_wrapper/dash_custom_components/__init__.py
dash_wrapper/dash_custom_components/components.py
dash_wrapper/dash_cytoscape/__init__.py
dash_wrapper/dash_cytoscape/_wrapper.py
dash_wrapper/dash_daq/__init__.py
dash_wrapper/dash_daq/_wrapper.py
dash_wrapper/dash_html_components/__init__.py
dash_wrapper/dash_html_components/_wrapper.py
dash_wrapper/dash_table/__init__.py
dash_wrapper/dash_table/_wrapper.py
dash_wrapper-0.2.0.dist-info/LICENSE
dash_wrapper-0.2.0.dist-info/METADATA
dash_wrapper-0.2.0.dist-info/WHEEL
dash_wrapper-0.2.0.dist-info/top_level.txt
dash_wrapper-0.2.0.dist-info/RECORD
