Metadata-Version: 2.1
Name: dash-wrapper
Version: 0.2.0
Summary: A wrapper around dash to extend the api defining the layout
Home-page: https://github.com/gioxc88/dash-wrapper
Author: gioxc88
Author-email: gioxc@hotmail.it
License: UNKNOWN
Platform: UNKNOWN
Classifier: Programming Language :: Python :: 3
Classifier: License :: OSI Approved :: MIT License
Classifier: Operating System :: OS Independent
Requires-Python: >=3.7
Requires-Dist: dash (>=1.0.1)
